<annotation>
	<folder>img2</folder>
	<filename>000+0498_brighter.jpg</filename>
	<path>E:\code\data\FX_data\sample\all\222\img2\000+0498_brighter.jpg</path>
	<source>
		<database>Unknown</database>
	</source>
	<size>
		<width>2650</width>
		<height>700</height>
		<depth>3</depth>
	</size>
	<segmented>0</segmented>
	<object>
		<name>damage</name>
		<pose>Unspecified</pose>
		<truncated>0</truncated>
		<difficult>0</difficult>
		<bndbox>
			<xmin>1231</xmin>
			<ymin>63</ymin>
			<xmax>1359</xmax>
			<ymax>113</ymax>
		</bndbox>
	</object>
	<object>
		<name>damage</name>
		<pose>Unspecified</pose>
		<truncated>0</truncated>
		<difficult>0</difficult>
		<bndbox>
			<xmin>806</xmin>
			<ymin>31</ymin>
			<xmax>877</xmax>
			<ymax>63</ymax>
		</bndbox>
	</object>
</annotation>
